classyfire_cli/__init__.py
classyfire_cli/cli.py
classyfire_cli/src/__init__.py
classyfire_cli/src/api.py
classyfire_cli/src/batch.py
classyfire_cli/src/utils.py
classyfire_cli-0.1.1.dist-info/LICENSE
classyfire_cli-0.1.1.dist-info/METADATA
classyfire_cli-0.1.1.dist-info/WHEEL
classyfire_cli-0.1.1.dist-info/entry_points.txt
classyfire_cli-0.1.1.dist-info/RECORD
